ai_import_plugin/__init__.py
ai_import_plugin/cms_app.py
ai_import_plugin-0.4.0.dist-info/METADATA
ai_import_plugin-0.4.0.dist-info/WHEEL
ai_import_plugin-0.4.0.dist-info/entry_points.txt
ai_import_plugin-0.4.0.dist-info/top_level.txt
ai_import_plugin-0.4.0.dist-info/RECORD
