Metadata-Version: 2.4
Name: ai-import-plugin
Version: 0.4.0
Summary: Django CMS plugin for Open edX to add an 'Import from AI' button
Classifier: Framework :: Django
Classifier: Programming Language :: Python :: 3
Requires-Dist: Django>=4.2.20
Dynamic: classifier
Dynamic: requires-dist
Dynamic: summary
